nowplaying/__init__.py
nowplaying/__main__.py
nowplaying/api.py
nowplaying/daemon.py
nowplaying/input/__init__.py
nowplaying/input/handler.py
nowplaying/input/observer.py
nowplaying/main.py
nowplaying/misc/__init__.py
nowplaying/misc/saemubox.py
nowplaying/options.py
nowplaying/otel.py
nowplaying/show/__init__.py
nowplaying/show/client.py
nowplaying/show/show.py
nowplaying/track/__init__.py
nowplaying/track/handler.py
nowplaying/track/observers/__init__.py
nowplaying/track/observers/base.py
nowplaying/track/observers/dab_audio_companion.py
nowplaying/track/observers/icecast.py
nowplaying/track/observers/scrobbler.py
nowplaying/track/observers/ticker.py
nowplaying/track/track.py
nowplaying/util.py
rabe_nowplaying-2.17.0.dist-info/LICENSE.txt
rabe_nowplaying-2.17.0.dist-info/METADATA
rabe_nowplaying-2.17.0.dist-info/WHEEL
rabe_nowplaying-2.17.0.dist-info/entry_points.txt
rabe_nowplaying-2.17.0.dist-info/RECORD
