Metadata-Version: 2.1
Name: rabe-nowplaying
Version: 2.17.0
Summary: Now Playing RaBe Songticker
Home-page: https://github.com/radiorabe/nowplaying
License: AGPL-3
Author: RaBe IT-Reaktion
Author-email: it@rabe.ch
Requires-Python: >=3.11,<4.0
Classifier: Development Status :: 5 - Production/Stable
Classifier: License :: OSI Approved :: GNU Affero General Public License v3
Classifier: License :: Other/Proprietary License
Classifier: Programming Language :: Python :: 3
Classifier: Programming Language :: Python :: 3.11
Requires-Dist: CherryPy (>=18.8.0,<19.0.0)
Requires-Dist: Werkzeug (>=2.3.6,<3.0.0)
Requires-Dist: cachecontrol (>=0.13.1,<0.14.0)
Requires-Dist: cachelib (>=0.10.1,<0.11.0)
Requires-Dist: cloudevents (>=1.9.0,<2.0.0)
Requires-Dist: configargparse (>=1.5.5,<2.0.0)
Requires-Dist: isodate (>=0.6.1,<0.7.0)
Requires-Dist: lxml (>=4.9.2,<5.0.0)
Requires-Dist: nowplaypadgen (>=0.4.9,<0.5.0)
Requires-Dist: opentelemetry-api (>=1.18.0,<2.0.0)
Requires-Dist: opentelemetry-exporter-otlp (>=1.18.0,<2.0.0)
Requires-Dist: opentelemetry-sdk (>=1.18.0,<2.0.0)
Requires-Dist: pylast (>=5.2.0,<6.0.0)
Requires-Dist: pytz (>=2023.3)
Requires-Dist: rabe-cridlib (>=0.10.1,<0.11.0)
Requires-Dist: requests (>=2.31.0,<3.0.0)
Project-URL: Repository, https://github.com/radiorabe/nowplaying
